rhubarb/__init__.py
rhubarb/constants.py
rhubarb/exceptions.py
rhubarb/settings.py
rhubarb/tasks.py
rhubarb-0.3.0.dist-info/licenses/LICENSE
rhubarb-0.3.0.dist-info/METADATA
rhubarb-0.3.0.dist-info/WHEEL
rhubarb-0.3.0.dist-info/top_level.txt
rhubarb-0.3.0.dist-info/RECORD
