Metadata-Version: 2.4
Name: rhubarb
Version: 0.3.0
Summary: Avoid running multiple instances of the same celery task concurrently
Home-page: https://github.com/RedHatProductSecurity/rhubarb/
Author: Adrian Torres, Red Hat Product Security
Author-email: atorresj@redhat.com
License: MIT
Project-URL: Source, https://github.com/RedHatProductSecurity/rhubarb/
Project-URL: Tracker, https://github.com/RedHatProductSecurity/rhubarb/issues
Keywords: celery redis lock redlock mutex task lockable duplicate prevent
Classifier: Development Status :: 4 - Beta
Classifier: License :: OSI Approved :: MIT License
Classifier: Programming Language :: Python :: 3
Classifier: Programming Language :: Python :: 3.8
Classifier: Programming Language :: Python :: 3.9
Classifier: Programming Language :: Python :: 3.10
Classifier: Programming Language :: Python :: 3.11
Classifier: Programming Language :: Python :: 3.12
Classifier: Intended Audience :: Developers
Classifier: Intended Audience :: Information Technology
Classifier: Environment :: Plugins
Classifier: Framework :: Celery
Classifier: Natural Language :: English
Classifier: Operating System :: OS Independent
Classifier: Topic :: Software Development :: Libraries
Classifier: Topic :: System :: Distributed Computing
Requires-Python: >=3.8
License-File: LICENSE
Requires-Dist: celery>=5.2.0
Requires-Dist: redis>=4.5.0
Dynamic: author
Dynamic: author-email
Dynamic: classifier
Dynamic: description
Dynamic: description-content-type
Dynamic: home-page
Dynamic: keywords
Dynamic: license
Dynamic: license-file
Dynamic: project-url
Dynamic: requires-dist
Dynamic: requires-python
Dynamic: summary
